tgb_seq/.DS_Store
tgb_seq/__init__.py
tgb_seq/LinkPred/__init__.py
tgb_seq/LinkPred/dataloader.py
tgb_seq/LinkPred/evaluator.py
tgb_seq/LinkPred/negsampler.py
tgb_seq/__pycache__/__init__.cpython-312.pyc
tgb_seq/datasets/__init__.py
tgb_seq/datasets/datasets_info.py
tgb_seq/datasets/preprocess.py
tgb_seq-0.1.2.dist-info/licenses/LICENSE
tgb_seq-0.1.2.dist-info/METADATA
tgb_seq-0.1.2.dist-info/WHEEL
tgb_seq-0.1.2.dist-info/top_level.txt
tgb_seq-0.1.2.dist-info/RECORD
