Metadata-Version: 2.4
Name: tgb_seq
Version: 0.1.2
Summary: Temporal Graph Benchmark with Sequential Dynamics
Author-email: Lu Yi <yilu@ruc.edu.cn>, Jie Peng <peng_jie@ruc.edu.cn>, Yanping Zheng <zhengyanping@ruc.edu.cn>, Fengran Mo <fengran.mo@umontreal.ca>, Zhewei Wei <zhewei@ruc.edu.cn>, YuHang Ye <yeyuhang@huawei.com>, Zixuan Yue <yuezixuan@huawei.com>, Zengfeng Huang <huangzf@fudan.edu.cn>
License: MIT License
Project-URL: Homepage, https://github.com/TGB-Seq/TGB-Seq
Project-URL: Documentation, https://github.com/TGB-Seq/TGB-Seq
Project-URL: Repository, https://github.com/TGB-Seq/TGB-Seq
Project-URL: Issues, https://github.com/TGB-Seq/TGB-Seq/issues
Classifier: Development Status :: 4 - Beta
Classifier: Intended Audience :: Developers
Classifier: Intended Audience :: Science/Research
Classifier: Programming Language :: Python :: 3
Classifier: Programming Language :: Python :: 3.9
Classifier: Programming Language :: Python :: 3.10
Classifier: Programming Language :: Python :: 3.11
Classifier: Programming Language :: Python :: 3.12
Classifier: Programming Language :: Python :: 3.13
Classifier: Topic :: Scientific/Engineering :: Artificial Intelligence
Requires-Python: >=3.9
License-File: LICENSE
Requires-Dist: datetime>=5.5
Requires-Dist: numpy>=2.0
Requires-Dist: pandas>=2.0.0
Requires-Dist: huggingface-hub>=0.26.0
Requires-Dist: torch>=2.3.0
Dynamic: license-file
